designer_news/__init__.py
designer_news-0.1.0.dist-info/DESCRIPTION.rst
designer_news-0.1.0.dist-info/METADATA
designer_news-0.1.0.dist-info/pydist.json
designer_news-0.1.0.dist-info/RECORD
designer_news-0.1.0.dist-info/top_level.txt
designer_news-0.1.0.dist-info/WHEEL
