Metadata-Version: 2.0
Name: designer-news
Version: 0.1.0
Summary: Python library for the Designer News API
Home-page: https://github.com/jpadilla/designer-news-python
Author: Jose Padilla
Author-email: hello@jpadilla.com
License: MIT
Keywords: designer news layervault
Platform: UNKNOWN
Classifier: Development Status :: 3 - Alpha
Classifier: Environment :: Web Environment
Classifier: Intended Audience :: Developers
Classifier: License :: OSI Approved :: MIT License
Classifier: Operating System :: OS Independent
Classifier: Programming Language :: Python
Classifier: Programming Language :: Python :: 2.6
Classifier: Programming Language :: Python :: 2.7
Classifier: Programming Language :: Python :: 3.2
Classifier: Programming Language :: Python :: 3.3
Classifier: Topic :: Utilities
Requires-Dist: requests (>=2.2.1)
